fastuv/__init__.py
fastuv/cli.py
fastuv/installer.py
fastuv/uninstaller.py
fastuv/utils.py
fastuv/hooks/conda_env.ps1
fastuv/hooks/conda_env.sh
fastuv/templates/powershell_injection.ps1
fastuv/templates/shell_injection.sh
fastuv-0.1.2.dist-info/METADATA
fastuv-0.1.2.dist-info/WHEEL
fastuv-0.1.2.dist-info/entry_points.txt
fastuv-0.1.2.dist-info/licenses/LICENSE
fastuv-0.1.2.dist-info/RECORD
