Metadata-Version: 2.4
Name: fastuv
Version: 0.1.2
Summary: Fast UV installer with China mirrors pre-configured - 预配置国内源的快速 uv 安装器
Project-URL: Homepage, https://github.com/whillhill/fastuv
Project-URL: Bug Reports, https://github.com/whillhill/fastuv/issues
Project-URL: Source, https://github.com/whillhill/fastuv
Author-email: whillhill <ooooofish@126.com>
License-Expression: MIT
License-File: LICENSE
Keywords: china,fast,mirror,package-manager,python,uv
Classifier: Development Status :: 4 - Beta
Classifier: Intended Audience :: Developers
Classifier: License :: OSI Approved :: MIT License
Classifier: Operating System :: OS Independent
Classifier: Programming Language :: Python :: 3
Classifier: Programming Language :: Python :: 3.8
Classifier: Programming Language :: Python :: 3.9
Classifier: Programming Language :: Python :: 3.10
Classifier: Programming Language :: Python :: 3.11
Classifier: Programming Language :: Python :: 3.12
Classifier: Topic :: Software Development :: Libraries :: Python Modules
Classifier: Topic :: System :: Installation/Setup
Requires-Python: >=3.8
Provides-Extra: dev
Requires-Dist: black; extra == 'dev'
Requires-Dist: isort; extra == 'dev'
Requires-Dist: mypy; extra == 'dev'
Requires-Dist: pytest>=6.0; extra == 'dev'
